build2vec/__init__.py
build2vec/build2vec.py
build2vec/dynabuild2vec.py
build2vec/ifc2graph.py
build2vec/parallel.py
build2vec-0.0.6.dist-info/LICENCE.txt
build2vec-0.0.6.dist-info/METADATA
build2vec-0.0.6.dist-info/WHEEL
build2vec-0.0.6.dist-info/top_level.txt
build2vec-0.0.6.dist-info/RECORD
