Metadata-Version: 2.1
Name: build2vec
Version: 0.0.6
Summary: Python package for building data embeddings
Home-page: UNKNOWN
Author: Mahmoud Abdelrahman
Author-email: <arch.mahmoud.ouf111@gmail.com>
License: UNKNOWN
Keywords: graph,network,building,spatial,spatiotemporal,bim,gis
Platform: UNKNOWN
Classifier: Development Status :: 1 - Planning
Classifier: Intended Audience :: Developers
Classifier: Programming Language :: Python :: 3
Classifier: Operating System :: Unix
Classifier: Operating System :: MacOS :: MacOS X
Classifier: Operating System :: Microsoft :: Windows
Requires-Dist: gensim
Requires-Dist: networkx
Requires-Dist: geopandas
Requires-Dist: tqdm
